hypervise/__init__.py
hypervise/base.py
hypervise-0.1.0a0.dist-info/LICENSE
hypervise-0.1.0a0.dist-info/METADATA
hypervise-0.1.0a0.dist-info/WHEEL
hypervise-0.1.0a0.dist-info/top_level.txt
hypervise-0.1.0a0.dist-info/RECORD
